pycff/__init__.py
pycff/__main__.py
pycff/application.cp313-win_amd64.pyd
pycff/cff.cp313-win_amd64.pyd
pycff/clevertw.cp313-win_amd64.pyd
pycff/clevertwitem.cp313-win_amd64.pyd
pycff/form_ui.cp313-win_amd64.pyd
pycff/resource_rc.cp313-win_amd64.pyd
pycff/widget.cp313-win_amd64.pyd
pycff/translations/PyCFF_en.qm
pycff/translations/PyCFF_zh_CN.qm
pycff-1.3.1.dist-info/licenses/LICENSE
pycff-1.3.1.dist-info/METADATA
pycff-1.3.1.dist-info/WHEEL
pycff-1.3.1.dist-info/entry_points.txt
pycff-1.3.1.dist-info/top_level.txt
pycff-1.3.1.dist-info/RECORD
