Metadata-Version: 2.4
Name: PyCFF
Version: 1.3.1
Summary: A function fitting tool
Author-email: Andrew Moa <Andrew.Moa2005@163.com>
License-Expression: LGPL-3.0-or-later
Project-URL: Homepage, https://github.com/AndrewMoa2005/PyCFF
Project-URL: Repository, https://github.com/AndrewMoa2005/PyCFF.git
Keywords: PySide6,application,widget
Classifier: Development Status :: 5 - Production/Stable
Classifier: Intended Audience :: Developers
Classifier: Programming Language :: Python :: 3
Classifier: Programming Language :: Python :: 3.12
Classifier: Programming Language :: Python :: 3.13
Classifier: Topic :: Scientific/Engineering :: Mathematics
Requires-Python: >=3.12
License-File: LICENSE
Requires-Dist: numpy
Requires-Dist: scipy
Requires-Dist: PySide6
Requires-Dist: openpyxl
Requires-Dist: xlrd
Requires-Dist: xlwt
Dynamic: license-file
